tusubtitulo/__init__.py
tusubtitulo/__main__.py
tusubtitulo/api.py
tusubtitulo/cli.py
tusubtitulo-0.0.20200213131340.dist-info/LICENSE.txt
tusubtitulo-0.0.20200213131340.dist-info/METADATA
tusubtitulo-0.0.20200213131340.dist-info/WHEEL
tusubtitulo-0.0.20200213131340.dist-info/entry_points.txt
tusubtitulo-0.0.20200213131340.dist-info/top_level.txt
tusubtitulo-0.0.20200213131340.dist-info/RECORD
