Metadata-Version: 2.1
Name: tusubtitulo
Version: 0.0.20200213131340
Summary: API and command line downloader for tusubtitulo.com
Home-page: https://github.com/ldotlopez/tusubtitulo
Author: Luis López
Author-email: luis@cuarentaydos.com
License: LICENSE.txt
Platform: UNKNOWN
Requires-Dist: babelfish (==0.5.5)
Requires-Dist: beautifulsoup4 (==4.8.2)
Requires-Dist: bs4 (==0.0.1)
Requires-Dist: certifi (==2019.11.28)
Requires-Dist: chardet (==3.0.4)
Requires-Dist: guessit (==3.1.0)
Requires-Dist: idna (==2.8)
Requires-Dist: python-dateutil (==2.8.1)
Requires-Dist: rebulk (==2.0.0)
Requires-Dist: requests (==2.22.0)
Requires-Dist: six (==1.14.0)
Requires-Dist: soupsieve (==1.9.5)
Requires-Dist: urllib3 (==1.25.8)
